validated_dc.py
validated_dc-1.3.3.dist-info/LICENSE
validated_dc-1.3.3.dist-info/METADATA
validated_dc-1.3.3.dist-info/WHEEL
validated_dc-1.3.3.dist-info/top_level.txt
validated_dc-1.3.3.dist-info/RECORD
