Metadata-Version: 2.1
Name: validated-dc
Version: 1.3.3
Summary: Dataclass with data validation.
Home-page: https://github.com/EvgeniyBurdin/validated_dc
Author: Evgeniy Burdin
Author-email: e.s.burdin@mail.ru
License: BSD
Keywords: validated dataclasses typing dict api
Platform: UNKNOWN
Classifier: Programming Language :: Python :: 3.7
Classifier: Programming Language :: Python :: 3.8
Classifier: Programming Language :: Python :: 3.9
Classifier: License :: OSI Approved :: BSD License
Classifier: Operating System :: OS Independent
Classifier: Topic :: Software Development
Requires-Python: >=3.7
